logt/__init__.py
logt/logt.py
logt-0.1.0.dist-info/METADATA
logt-0.1.0.dist-info/WHEEL
logt-0.1.0.dist-info/top_level.txt
logt-0.1.0.dist-info/RECORD
