Metadata-Version: 2.1
Name: logt
Version: 0.1.0
Summary: logt launching soon
Home-page: UNKNOWN
Author: Soham Chakraborty
License: AGPLv3
Platform: UNKNOWN
